pmjsonparser/cli.py
pmjsonparser/parser.py
pmjsonparser-1.0.0.dist-info/METADATA
pmjsonparser-1.0.0.dist-info/WHEEL
pmjsonparser-1.0.0.dist-info/entry_points.txt
pmjsonparser-1.0.0.dist-info/top_level.txt
pmjsonparser-1.0.0.dist-info/RECORD
