Metadata-Version: 2.1
Name: pmjsonparser
Version: 1.0.0
Summary: UNKNOWN
License: UNKNOWN
Platform: UNKNOWN
Classifier: Programming Language :: Python :: 3.6
Requires-Dist: argparse (~=1.4.0)
